{
  "seed": "270",
  "nightlord": "Caligo",
  "patternIndex": 271,
  "pois": [
    {
      "poiKey": "Castle",
      "label": "Banished Knights",
      "poiId": 23,
      "coordinates": [
        1291.88,
        915.88
      ]
    },
    {
      "poiKey": "Major Base",
      "label": "Camp - Elder Lion",
      "poiId": null,
      "coordinates": null
    },
    {
      "poiKey": "Minor Base",
      "label": "Sorcerer's Rise - Unlit Candle",
      "poiId": null,
      "coordinates": null
    },
    {
      "poiKey": "Evergaol",
      "label": "Banished Knights",
      "poiId": null,
      "coordinates": null
    },
    {
      "poiKey": "Arena Boss",
      "label": "Red Wolf",
      "poiId": null,
      "coordinates": null
    },
    {
      "poiKey": "Field Boss",
      "label": "Death Rite Bird",
      "poiId": null,
      "coordinates": null
    },
    {
      "poiKey": "Rotted Woods",
      "label": "Tree Sentinel",
      "poiId": null,
      "coordinates": null
    },
    {
      "poiKey": "Rot Blessing",
      "label": "West",
      "poiId": null,
      "coordinates": null
    }
  ]
}